bvx_oop/__init__.py
bvx_oop/singleton.py
bvx_oop-0.0.9.dist-info/LICENSE
bvx_oop-0.0.9.dist-info/METADATA
bvx_oop-0.0.9.dist-info/WHEEL
bvx_oop-0.0.9.dist-info/top_level.txt
bvx_oop-0.0.9.dist-info/RECORD
