Metadata-Version: 2.1
Name: bvx-oop
Version: 0.0.9
Summary: Object-Oriented Programming classes.
Home-page: https://github.com/kotsutsumi/bvx-oop
Author: Kazuhiro Kotsutsumi
License: The MIT License
Platform: UNKNOWN
License-File: LICENSE
